fastapi_frl/__init__.py
fastapi_frl/backend.py
fastapi_frl/key.py
fastapi_frl/limiter.py
fastapi_frl/algorithms/__init__.py
fastapi_frl/algorithms/base.py
fastapi_frl/algorithms/bucket.py
fastapi_frl/algorithms/simple.py
fastapi_frl/algorithms/window.py
fastapi_frl-0.0.5.dist-info/LICENSE
fastapi_frl-0.0.5.dist-info/METADATA
fastapi_frl-0.0.5.dist-info/WHEEL
fastapi_frl-0.0.5.dist-info/top_level.txt
fastapi_frl-0.0.5.dist-info/RECORD
